AUTHORS.rst
CONTRIBUTING.rst
HISTORY.rst
LICENSE
MANIFEST.in
README.rst
setup.cfg
setup.py
defaultsob/__init__.py
defaultsob/core.py
defaultsob.egg-info/PKG-INFO
defaultsob.egg-info/SOURCES.txt
defaultsob.egg-info/dependency_links.txt
defaultsob.egg-info/not-zip-safe
defaultsob.egg-info/top_level.txt
docs/Makefile
docs/authors.rst
docs/conf.py
docs/contributing.rst
docs/history.rst
docs/index.rst
docs/installation.rst
docs/make.bat
docs/readme.rst
docs/usage.rst
tests/__init__.py
tests/test_defaults_defaults.py