Metadata-Version: 1.1
Name: defaultsob
Version: 0.3.0
Summary: A simple package to create data structures with defaultsob
Home-page: https://github.com/honewatson/defaultsob
Author: Hone Watson
Author-email: comments@hone.be
License: ISCL
Keywords: defaultsob,data structures,objects
Platform: UNKNOWN
Classifier: Development Status :: 2 - Pre-Alpha
Classifier: Intended Audience :: Developers
Classifier: License :: OSI Approved :: ISC License (ISCL)
Classifier: Natural Language :: English
Classifier: Programming Language :: Python :: 2
Classifier: Programming Language :: Python :: 2.7
